<?xml version="1.0" encoding="utf-8"?>
<rdf:RDF
    xmlns="http://purl.org/rss/1.0/"
    xmlns:rdf="http://www.w3.org/1999/02/22-rdf-syntax-ns#"
    xmlns:slash="http://purl.org/rss/1.0/modules/slash/"
    xmlns:dc="http://purl.org/dc/elements/1.1/">
    <channel rdf:about="https://www.cnn.co.jp">
        <title>国際ニュース - CNN.co.jp</title>
        <description>CNN.co.jpはCNN.com日本語訳サイトです</description>
        <link>https://www.cnn.co.jp</link>
       <dc:date>2025-11-25T15:43:00+09:00</dc:date>
        <items>
            <rdf:Seq>
                <rdf:li rdf:resource="https://www.cnn.co.jp/world/35240854.html?ref=rss"/>
                <rdf:li rdf:resource="https://www.cnn.co.jp/usa/35240852.html?ref=rss"/>
                <rdf:li rdf:resource="https://www.cnn.co.jp/usa/35240849.html?ref=rss"/>
                <rdf:li rdf:resource="https://www.cnn.co.jp/world/35240846.html?ref=rss"/>
                <rdf:li rdf:resource="https://www.cnn.co.jp/style/fashion/35240844.html?ref=rss"/>
                <rdf:li rdf:resource="https://www.cnn.co.jp/world/35240843.html?ref=rss"/>
                <rdf:li rdf:resource="https://www.cnn.co.jp/usa/35240840.html?ref=rss"/>
                <rdf:li rdf:resource="https://www.cnn.co.jp/usa/35240841.html?ref=rss"/>
                <rdf:li rdf:resource="https://www.cnn.co.jp/showbiz/35240838.html?ref=rss"/>
                <rdf:li rdf:resource="https://www.cnn.co.jp/world/35240836.html?ref=rss"/>
                <rdf:li rdf:resource="https://www.cnn.co.jp/usa/35240831.html?ref=rss"/>
                <rdf:li rdf:resource="https://www.cnn.co.jp/world/35240828.html?ref=rss"/>
                <rdf:li rdf:resource="https://www.cnn.co.jp/world/35240824.html?ref=rss"/>
                <rdf:li rdf:resource="https://www.cnn.co.jp/fringe/35240647.html?ref=rss"/>
                <rdf:li rdf:resource="https://www.cnn.co.jp/showbiz/35240823.html?ref=rss"/>
                <rdf:li rdf:resource="https://www.cnn.co.jp/fringe/35240822.html?ref=rss"/>
                <rdf:li rdf:resource="https://www.cnn.co.jp/world/35240821.html?ref=rss"/>
                <rdf:li rdf:resource="https://www.cnn.co.jp/fringe/35240819.html?ref=rss"/>
                <rdf:li rdf:resource="https://www.cnn.co.jp/showbiz/35240820.html?ref=rss"/>
                <rdf:li rdf:resource="https://www.cnn.co.jp/usa/35240818.html?ref=rss"/>
                <rdf:li rdf:resource="https://www.cnn.co.jp/world/35240816.html?ref=rss"/>
                <rdf:li rdf:resource="https://www.cnn.co.jp/world/35240815.html?ref=rss"/>
                <rdf:li rdf:resource="https://www.cnn.co.jp/fringe/35240810.html?ref=rss"/>
                <rdf:li rdf:resource="https://www.cnn.co.jp/tech/35240809.html?ref=rss"/>
                <rdf:li rdf:resource="https://www.cnn.co.jp/world/35240808.html?ref=rss"/>
                <rdf:li rdf:resource="https://www.cnn.co.jp/world/35240807.html?ref=rss"/>
                <rdf:li rdf:resource="https://www.cnn.co.jp/world/35240806.html?ref=rss"/>
                <rdf:li rdf:resource="https://www.cnn.co.jp/travel/35240804.html?ref=rss"/>
                <rdf:li rdf:resource="https://www.cnn.co.jp/usa/35240805.html?ref=rss"/>
                <rdf:li rdf:resource="https://www.cnn.co.jp/fringe/35240803.html?ref=rss"/>
            </rdf:Seq>
        </items>
    </channel>
    <item rdf:about="https://www.cnn.co.jp/world/35240854.html?ref=rss">
        <dc:format>text/html</dc:format>
        <dc:date>2025-11-25T15:43:00+09:00</dc:date>
        <title>米軍無人機「リーパー」、韓国沖で墜落</title>
        <link>https://www.cnn.co.jp/world/35240854.html?ref=rss</link>
        <description>韓国に常時配備された米空軍無人機飛行隊の1機が、24日未明、韓国西岸沖で墜落した。軍の声明およびメディアの報道で明らかになった。

空軍第8戦闘航空団の声明によると、群山空軍基地に配備されている無人機「MQ9リーパー」はマルドリ島付近で「通常任務中に事故に遭った」。事故の原因は現在調査中。

複数の地元メディアは、この無人機が墜落したと報じている。

無人機は群山の第431遠征偵察飛行隊に配備されていた。同飛...&lt;br clear='left'&gt;&lt;a href='https://www.cnn.co.jp/world/35240854.html?ref=rss'&gt;&lt;img src='https://www.cnn.co.jp/storage/2025/11/25/1c12f79198a7a880ee634e603c4a236b/t/768/510/d/241023-f-oo000-1026.jpeg'&gt;&lt;/a&gt;</description>
    </item>
    <item rdf:about="https://www.cnn.co.jp/usa/35240852.html?ref=rss">
        <dc:format>text/html</dc:format>
        <dc:date>2025-11-25T15:11:00+09:00</dc:date>
        <title>米連邦地裁、トランプ大統領「政敵」の起訴を棄却　担当検察官の任命が違法</title>
        <link>https://www.cnn.co.jp/usa/35240852.html?ref=rss</link>
        <description>米連邦地裁は24日、ドナルド・トランプ大統領にとっての「政敵」とされるジェームズ・コミー元連邦捜査局（FBI）長官とニューヨーク州のレティシア・ジェームズ州司法長官に対する起訴を棄却した。

連邦地裁判事は、トランプ氏がリンジー・ハリガン氏を臨時の検察官に任命した手続きが無効だったと判断した。

トランプ氏は、コミー氏やジェームズ氏といった政敵に対する刑事訴追を求める圧力が高まる中で、ハリガン氏を検察官...&lt;br clear='left'&gt;&lt;a href='https://www.cnn.co.jp/usa/35240852.html?ref=rss'&gt;&lt;img src='https://www.cnn.co.jp/storage/2025/11/25/7e92b11d02a32c337480088d64ab9baa/t/768/432/d/letitiajamesjamescomey.jpg'&gt;&lt;/a&gt;</description>
    </item>
    <item rdf:about="https://www.cnn.co.jp/usa/35240849.html?ref=rss">
        <dc:format>text/html</dc:format>
        <dc:date>2025-11-25T14:50:00+09:00</dc:date>
        <title>トランプ氏、習主席と「とても良い電話会談」　ウクライナ情勢を協議</title>
        <link>https://www.cnn.co.jp/usa/35240849.html?ref=rss</link>
        <description>米国のドナルド・トランプ大統領は24日、中国の習近平（シーチンピン）国家主席と「とても良い電話会談」を行い、その中でウクライナとロシアについて協議したと明らかにした。

大統領はSNS「トゥルース・ソーシャル」に「中国の習主席と、とても良い電話会談をした」と投稿。ウクライナとロシア、合成麻薬フェンタニル、大豆やそのほかの農産品などさまざまな議題を話し合ったとした。

中国とロシア、そして両国の指導者は近...&lt;br clear='left'&gt;&lt;a href='https://www.cnn.co.jp/usa/35240849.html?ref=rss'&gt;&lt;img src='https://www.cnn.co.jp/storage/2025/11/25/74f5c696ffa6275a21f346ba8ed0dcc7/t/768/432/d/trumpxi-split.jpg'&gt;&lt;/a&gt;</description>
    </item>
    <item rdf:about="https://www.cnn.co.jp/world/35240846.html?ref=rss">
        <dc:format>text/html</dc:format>
        <dc:date>2025-11-25T13:25:00+09:00</dc:date>
        <title>米提案の和平案、「原則として解決の基礎となり得る」　プーチン氏</title>
        <link>https://www.cnn.co.jp/world/35240846.html?ref=rss</link>
        <description>ロシアのプーチン大統領は24日、トルコのエルドアン大統領と電話協議を行った。クレムリン（ロシア大統領府）が公表した電話会談の記録によれば、プーチン氏は、ウクライナでの戦争をめぐり、米国が提示した「和平案」の一つが「原則として、最終的な平和的解決の基礎となり得る」との見方を示した。

発表によると、プーチン氏とエルドアン氏は米国の和平案について協議した。プーチン氏はロシア側が検討した案が、米アラスカ...&lt;br clear='left'&gt;&lt;a href='https://www.cnn.co.jp/world/35240846.html?ref=rss'&gt;&lt;img src='https://www.cnn.co.jp/storage/2025/11/25/1252dd64b7cccbd4752033b65cd68fd3/t/768/511/d/large-gettyimages-2245854930.jpg'&gt;&lt;/a&gt;</description>
    </item>
    <item rdf:about="https://www.cnn.co.jp/style/fashion/35240844.html?ref=rss">
        <dc:format>text/html</dc:format>
        <dc:date>2025-11-25T13:02:00+09:00</dc:date>
        <title>ファッションの世界的祭典「メットガラ」、来年のメインスポンサーに非難集中</title>
        <link>https://www.cnn.co.jp/style/fashion/35240844.html?ref=rss</link>
        <description>2026年にニューヨークのメトロポリタン美術館（MET）で開かれるファッションイベント「メットガラ」のスポンサーを務めるローレン・サンチェス・ベゾス氏の役割をめぐり、批判が高まっている。ヴォーグ米国版の編集長を退いたアナ・ウィンター氏はこのことについて問われた際、慈善家で元ジャーナリストのサンチェス・ベゾス氏を「衣装、そしてもちろんファッションを強く愛している人」と評した。

ヴォーグイタリア版の元編集...&lt;br clear='left'&gt;&lt;a href='https://www.cnn.co.jp/style/fashion/35240844.html?ref=rss'&gt;&lt;img src='https://www.cnn.co.jp/storage/2025/11/25/d6047af507f1ac9d40f3825ce1072566/t/768/500/d/gettyimages-2151790995.jpg'&gt;&lt;/a&gt;</description>
    </item>
    <item rdf:about="https://www.cnn.co.jp/world/35240843.html?ref=rss">
        <dc:format>text/html</dc:format>
        <dc:date>2025-11-25T12:22:00+09:00</dc:date>
        <title>英国のキャメロン元首相、前立腺がんの診断を告白　検査の普及呼びかけ</title>
        <link>https://www.cnn.co.jp/world/35240843.html?ref=rss</link>
        <description>英国のデービッド・キャメロン元首相（59）が前立腺がんと診断され、治療を受けていることを明らかにした。自身の診断を受け、リスクの高い男性に照準を絞った検査の普及を呼びかけている。

23日の英紙タイムズに掲載されたインタビューの中でキャメロン氏は、妻の勧めで前立腺がんの検査を受けたと告白。まず前立腺がんに関係するたんぱく質の値を調べる（前立腺特異抗原＝PSA）検査を受けた結果、PSAスコアが高いと診断され...&lt;br clear='left'&gt;&lt;a href='https://www.cnn.co.jp/world/35240843.html?ref=rss'&gt;&lt;img src='https://www.cnn.co.jp/storage/2025/11/25/5563b1ef68360dbbf00ec15d104daa84/t/768/512/d/large-gettyimages-2245369337.jpg'&gt;&lt;/a&gt;</description>
    </item>
    <item rdf:about="https://www.cnn.co.jp/usa/35240840.html?ref=rss">
        <dc:format>text/html</dc:format>
        <dc:date>2025-11-25T11:48:00+09:00</dc:date>
        <title>同級生メッタ刺し事件の加害女性を240キロ離れた場所で拘束、前日に施設抜け出す　米</title>
        <link>https://www.cnn.co.jp/usa/35240840.html?ref=rss</link>
        <description>学校6年生の女児が2014年、インターネットの架空キャラクター「スレンダーマン」に気に入られたいという理由で同級生をメッタ刺しにして全米を震撼（しんかん）させた事件で殺人未遂の罪に問われた女性（23）がウィスコンシン州マディソンの施設から抜け出した事案で、女性が約240キロ離れたイリノイ州で発見され、拘束された。

マディソンの警察によれば、女性は22日夜、監視用のブレスレットを切断した後、行方不明になって...&lt;br clear='left'&gt;&lt;a href='https://www.cnn.co.jp/usa/35240840.html?ref=rss'&gt;&lt;img src='https://www.cnn.co.jp/storage/2025/11/25/84a0fac8cae2693358a11ff6eb1cd927/t/768/599/d/large-slenderman-killer.jpg'&gt;&lt;/a&gt;</description>
    </item>
    <item rdf:about="https://www.cnn.co.jp/usa/35240841.html?ref=rss">
        <dc:format>text/html</dc:format>
        <dc:date>2025-11-25T11:25:00+09:00</dc:date>
        <title>住宅地を襲った竜巻、100棟あまり損壊　住民の捜索活動続く　米テキサス州</title>
        <link>https://www.cnn.co.jp/usa/35240841.html?ref=rss</link>
        <description>米テキサス州ヒューストン地域で現地時間の24日午後、竜巻が発生し、住宅100棟以上が損壊した。地元当局がフェイスブックへの投稿で明らかにした。

当局は住民が負傷したり下敷きになったりした可能性もあるとみて、捜索活動を続けている。

米国立気象局（NWS）は同州ハリス郡で竜巻が発生したことを確認した。

ヒューストン地域ではこの日、大気の状態が不安定になって激しい雷雨が発達し、複数の竜巻の発生が伝えられてい...&lt;br clear='left'&gt;&lt;a href='https://www.cnn.co.jp/usa/35240841.html?ref=rss'&gt;&lt;img src='https://www.cnn.co.jp/storage/2025/11/25/d49390c54f784b4c47cc4d9f102af327/t/768/512/d/587319820-1298091499019231-2287277509212546592-n.jpg'&gt;&lt;/a&gt;</description>
    </item>
    <item rdf:about="https://www.cnn.co.jp/showbiz/35240838.html?ref=rss">
        <dc:format>text/html</dc:format>
        <dc:date>2025-11-25T10:34:00+09:00</dc:date>
        <title>ジャマイカのレゲエ歌手ジミー・クリフさん死去、81歳　「ザ・ハーダー・ゼイ・カム」</title>
        <link>https://www.cnn.co.jp/showbiz/35240838.html?ref=rss</link>
        <description>滑らかな歌声でレゲエというジャンルの普及に貢献した歌手のジミー・クリフさんが死去した。81歳だった。妻のラティファ・チェンバースさんが24日、SNSで明らかにした。

チェンバースさんは「深い悲しみとともに、夫のジミー・クリフが発作とそれに続く肺炎のためこの世を去ったことをお知らせします」と投稿した。「彼とともに歩んでくれた家族、友人、アーティスト仲間、同僚たちに感謝します。世界中のファンのみなさん、み...&lt;br clear='left'&gt;&lt;a href='https://www.cnn.co.jp/showbiz/35240838.html?ref=rss'&gt;&lt;img src='https://www.cnn.co.jp/storage/2025/11/25/acd9c064e27efa75da458cfc1b4f693b/t/768/493/d/large-gettyimages-84883404.jpg'&gt;&lt;/a&gt;</description>
    </item>
    <item rdf:about="https://www.cnn.co.jp/world/35240836.html?ref=rss">
        <dc:format>text/html</dc:format>
        <dc:date>2025-11-25T10:07:00+09:00</dc:date>
        <title>ニュージーランド、2050年までにノネコ根絶へ　生物多様性保護目指す</title>
        <link>https://www.cnn.co.jp/world/35240836.html?ref=rss</link>
        <description>ニュージーランドは生物多様性を守る取り組みの一環として、2050年までにノネコの根絶を目指す計画を発表した。

タマ・ポタカ自然保全相は20日、ラジオ・ニュージーランドの番組の中で、ノネコを「冷徹な殺し屋」と形容。鳥類やコウモリ、トカゲ、昆虫などの種を脅かす捕食動物の根絶を目的とした「プレデターフリー2050」の対象にノネコを加えると発表した。

根絶対象にはオコジョ、フェレット、イタチ、ネズミ、ポッサムな...&lt;br clear='left'&gt;&lt;a href='https://www.cnn.co.jp/world/35240836.html?ref=rss'&gt;&lt;img src='https://www.cnn.co.jp/storage/2025/11/25/f9de84ba95bea4410d4fe8c62acb7afa/t/768/512/d/gettyimages-2196291685.jpg'&gt;&lt;/a&gt;</description>
    </item>
    <item rdf:about="https://www.cnn.co.jp/usa/35240831.html?ref=rss">
        <dc:format>text/html</dc:format>
        <dc:date>2025-11-25T09:29:00+09:00</dc:date>
        <title>「消滅」したとされるDOGE、分かっていることと分かっていないこと</title>
        <link>https://www.cnn.co.jp/usa/35240831.html?ref=rss</link>
        <description>トランプ政権当局者は、政府効率化省（DOGE）がもはや「中央集権的な」組織として運営されていないことを認めた。一方で、政権を象徴するコスト削減策の「原則」は健在だと主張している。

ロイター通信が23日に報じたところによると、DOGEはトランプ大統領が1月に署名した大統領令で定められた期限まで8カ月を残して「解散」した。大統領令は、既存の連邦機関デジタルサービス局（USDS）を再編し、ＤＯＧＥサービスと改名する...&lt;br clear='left'&gt;&lt;a href='https://www.cnn.co.jp/usa/35240831.html?ref=rss'&gt;&lt;img src='https://www.cnn.co.jp/storage/2025/11/25/c46296928f2c4336d7feaaa79664ed5d/t/768/512/d/gettyimages-2217852298-20251124202403966.jpg'&gt;&lt;/a&gt;</description>
    </item>
    <item rdf:about="https://www.cnn.co.jp/world/35240828.html?ref=rss">
        <dc:format>text/html</dc:format>
        <dc:date>2025-11-25T08:00:00+09:00</dc:date>
        <title>ゼレンスキー氏、各国指導者に相次ぎ謝意　トランプ氏の「全く感謝していない」批判受け</title>
        <link>https://www.cnn.co.jp/world/35240828.html?ref=rss</link>
        <description>ウクライナのゼレンスキー大統領は24日、SNSで世界の指導者らに対し、感謝の意を表明した。この前日には、トランプ米大統領がウクライナの指導部について米国主導の和平努力に「全く感謝していない」と批判していた。

ゼレンスキー氏は現地時間24日夜、約1時間の間にX（旧ツイッター）で世界の指導者ら13人に対し謝意を示し、複数のSNS投稿に「支援に感謝する！」と返信した。

ゼレンスキー氏が称賛した相手には、エストニア...&lt;br clear='left'&gt;&lt;a href='https://www.cnn.co.jp/world/35240828.html?ref=rss'&gt;&lt;img src='https://www.cnn.co.jp/storage/2025/11/25/470a26e60d19a010b73b53f806ae39f6/t/768/512/d/ap25325619978339-20251124194357477.jpg'&gt;&lt;/a&gt;</description>
    </item>
    <item rdf:about="https://www.cnn.co.jp/world/35240824.html?ref=rss">
        <dc:format>text/html</dc:format>
        <dc:date>2025-11-24T18:33:00+09:00</dc:date>
        <title>人里離れた森で生活する5人家族、子ども「保護」で裁判所が介入　イタリア</title>
        <link>https://www.cnn.co.jp/world/35240824.html?ref=rss</link>
        <description>イタリア中部の人里離れた森の中で、5人家族が送電網に頼らない生活を送っていたが、裁判所が介入し、その暮らしが行き詰まっている。

イタリアの森で馬やロバ、ニワトリとともに暮らしている「牧歌的」を自称するこの家族に対し、裁判所は子どもたちの保護を命じ、教会が運営する施設に移すよう指示した。アブルッツォ州の自宅から子どもたちを引き離すため、警察が派遣された。母親は同じ施設に滞在しているものの、両親の子...&lt;br clear='left'&gt;&lt;a href='https://www.cnn.co.jp/world/35240824.html?ref=rss'&gt;&lt;img src='https://www.cnn.co.jp/storage/2025/11/24/c467cd6e3cd8c257c18f6644117c6ef7/t/768/689/d/large-001-img-3302-1-blur.jpg'&gt;&lt;/a&gt;</description>
    </item>
    <item rdf:about="https://www.cnn.co.jp/fringe/35240647.html?ref=rss">
        <dc:format>text/html</dc:format>
        <dc:date>2025-11-24T17:30:00+09:00</dc:date>
        <title>最古のRNA配列、4万年前のマンモスの最期の詳細を明らかに</title>
        <link>https://www.cnn.co.jp/fringe/35240647.html?ref=rss</link>
        <description>現在のシベリアで約4万年前に死んだ若いマンモス「ユカ」から古代のリボ核酸（RNA）が採取された。こうした生物学的な遺物が、マンモスの最期の瞬間に関する洞察を提供している。

今回のRNAは、永久凍土で何千年も極めて良好に保存されていたミイラ化した脚部の組織から抽出された。これほど古いRNAが解析された例は初めてで、研究者は死亡時にどの遺伝子が活性化していたのかを明らかにしようとしている。

「生物のすべての...&lt;br clear='left'&gt;&lt;a href='https://www.cnn.co.jp/fringe/35240647.html?ref=rss'&gt;&lt;img src='https://www.cnn.co.jp/storage/2025/11/19/bb243b09ebea05e9eff29f3b6cb30144/t/768/508/d/mammoth-yuka-3.jpg'&gt;&lt;/a&gt;</description>
    </item>
    <item rdf:about="https://www.cnn.co.jp/showbiz/35240823.html?ref=rss">
        <dc:format>text/html</dc:format>
        <dc:date>2025-11-24T16:57:00+09:00</dc:date>
        <title>安青錦が大相撲九州場所で優勝、ウクライナから避難してきた21歳</title>
        <link>https://www.cnn.co.jp/showbiz/35240823.html?ref=rss</link>
        <description>大相撲九州場所千秋楽が23日にあり、関脇安青錦（あおにしき）（21）＝本名ヤブグシシン・ダニーロ、ウクライナ出身、安治川部屋＝が初優勝を遂げた。競争の激しい角界での急成長ぶりが称賛されている。

安青錦は優勝決定戦で、モンゴル出身の横綱豊昇龍を破った。

安青錦は取組後に、言葉では言い表せない気持ちだと喜びを語った。

ウクライナでは古くから格闘技が盛んで、オリンピックで多くのメダリストを輩出してきた。...&lt;br clear='left'&gt;&lt;a href='https://www.cnn.co.jp/showbiz/35240823.html?ref=rss'&gt;&lt;img src='https://www.cnn.co.jp/storage/2025/11/24/73bbae14ed75b38af52732a8b3d01ca6/t/768/511/d/gettyimages-2247499022.jpg'&gt;&lt;/a&gt;</description>
    </item>
    <item rdf:about="https://www.cnn.co.jp/fringe/35240822.html?ref=rss">
        <dc:format>text/html</dc:format>
        <dc:date>2025-11-24T15:45:00+09:00</dc:date>
        <title>好奇心旺盛な小学生から質問攻めにされたバス運転手、10年後に同僚として再会　米</title>
        <link>https://www.cnn.co.jp/fringe/35240822.html?ref=rss</link>
        <description>ジョイ・ケンリーさんは長年にわたり、米首都ワシントンで、ラッシュアワーにメトロバスの扉を開けて、連邦政府職員やビジネスパーソンを迎え入れてきた。これから1日が始まる乗客はたいてい無言でバスに乗り込んできた。

毎日同じ顔ぶれを目にするなか、1人の通勤客が記憶に残るようになった。この乗客は、議員でも有力なロビイストでもなく、小学5年生のサム・メンシマーさんだった。

しかも、とても好奇心旺盛な少年だった...&lt;br clear='left'&gt;&lt;a href='https://www.cnn.co.jp/fringe/35240822.html?ref=rss'&gt;&lt;img src='https://www.cnn.co.jp/storage/2025/11/24/56d7a9a03e9ed05d139a8066539582ca/t/768/432/d/cmetro-11202025-2v6a9420.jpg'&gt;&lt;/a&gt;</description>
    </item>
    <item rdf:about="https://www.cnn.co.jp/world/35240821.html?ref=rss">
        <dc:format>text/html</dc:format>
        <dc:date>2025-11-24T13:46:00+09:00</dc:date>
        <title>米、ウクライナと「生産的」な協議　トランプ氏は指導部を非難</title>
        <link>https://www.cnn.co.jp/world/35240821.html?ref=rss</link>
        <description>米国のルビオ国務長官は23日、ウクライナでの戦争の終結を目指してスイス・ジュネーブで米国とウクライナの代表団が行った協議について、「生産的だった」と語り、楽観的な見方を示した。

ルビオ氏は協議後、記者団に対し、今回の初会合は「これまでで最も生産的で意味のあるものだった」と述べた。

ルビオ氏は、トランプ米大統領が提示した28項目の「和平案」について、ウクライナとロシアの双方に受け入れ可能な条件に近づ...&lt;br clear='left'&gt;&lt;a href='https://www.cnn.co.jp/world/35240821.html?ref=rss'&gt;&lt;img src='https://www.cnn.co.jp/storage/2025/11/24/caab480c4b43a9e318d1a50481059ec5/t/768/511/d/large-c-gettyimages-2247555200.jpg'&gt;&lt;/a&gt;</description>
    </item>
    <item rdf:about="https://www.cnn.co.jp/fringe/35240819.html?ref=rss">
        <dc:format>text/html</dc:format>
        <dc:date>2025-11-24T12:03:00+09:00</dc:date>
        <title> 【CNN.co.jp1週間まとめ】「偽カルボナーラ」にイタリア激怒など（25年11月17～23日）</title>
        <link>https://www.cnn.co.jp/fringe/35240819.html?ref=rss</link>
        <description>CNN.co.jpでは米国政治を中心にサイエンスやスポーツ、エンタメなど幅広く海外の情報をお届けしています。

先週はどんな記事がよく読まれたのでしょうか。11月17日から11月23日の週間ランキングトップ5をご紹介します。

第5位：ビットコインが記録的高値から一転　溶け続ける理由は


  

  
米国株式は18日に下落して取引を終え、最近の下落傾向をさらに拡大させた/Pat Batard/Hans Lucas/AFP/Getty Images via CNN Newsourc...&lt;br clear='left'&gt;&lt;a href='https://www.cnn.co.jp/fringe/35240819.html?ref=rss'&gt;&lt;img src='https://www.cnn.co.jp/storage/2025/11/21/89c7dc4d9b90634eebfaa1fba98af1c1/t/768/512/d/gettyimages-2210097258.jpg'&gt;&lt;/a&gt;</description>
    </item>
    <item rdf:about="https://www.cnn.co.jp/showbiz/35240820.html?ref=rss">
        <dc:format>text/html</dc:format>
        <dc:date>2025-11-24T11:58:00+09:00</dc:date>
        <title>映画「ウィキッド　永遠の約束」、公開初週の興収235億円</title>
        <link>https://www.cnn.co.jp/showbiz/35240820.html?ref=rss</link>
        <description>ユニバーサルの新作映画「ウィキッド　永遠の約束」は公開初週の北米市場で興行収入1億5000万ドル（約235億円）を記録し、ランキングで首位に立った。今回の成績は昨年の感謝祭前の週末に公開された前作「ウィキッド　ふたりの魔女」の公開初週の興収1億1400万ドルを上回った。新作の世界市場での興収は2億2600万ドルだった。

調査会社コムスコアのポール・ダーガラベディアン氏は「続編が初週で前作を上回るとは限らない」と...&lt;br clear='left'&gt;&lt;a href='https://www.cnn.co.jp/showbiz/35240820.html?ref=rss'&gt;&lt;img src='https://www.cnn.co.jp/storage/2025/11/24/5299c57cfe676ce8879b42313cc8c4f5/t/768/511/d/large-2552-d085-00216r.jpg'&gt;&lt;/a&gt;</description>
    </item>
    <item rdf:about="https://www.cnn.co.jp/usa/35240818.html?ref=rss">
        <dc:format>text/html</dc:format>
        <dc:date>2025-11-24T11:01:00+09:00</dc:date>
        <title>同級生メッタ刺し事件の加害女性、施設抜け出して行方不明に　米</title>
        <link>https://www.cnn.co.jp/usa/35240818.html?ref=rss</link>
        <description>小学校6年生の女児が2014年、インターネットの架空キャラクター「スレンダーマン」に気に入られたいという理由で同級生をメッタ刺しにして全米を震撼（しんかん）させた事件で、殺人未遂の罪に問われた女性（23）が装着されていた監視用ブレスレットを破棄して、ウィスコンシン州マディソンの施設から抜け出した。警察が明らかにした。

警察によると、女性はマディソン西部の住宅街で22日午後8時ごろ、大人の知人と一緒にいる...&lt;br clear='left'&gt;&lt;a href='https://www.cnn.co.jp/usa/35240818.html?ref=rss'&gt;&lt;img src='https://www.cnn.co.jp/storage/2025/11/24/3c1ca636487881755cc784f4913d45b5/t/768/599/d/large-slenderman-killer.jpg'&gt;&lt;/a&gt;</description>
    </item>
    <item rdf:about="https://www.cnn.co.jp/world/35240816.html?ref=rss">
        <dc:format>text/html</dc:format>
        <dc:date>2025-11-24T10:30:00+09:00</dc:date>
        <title>武装集団に誘拐された子ども50人が脱出、250人以上は今も拉致　ナイジェリア</title>
        <link>https://www.cnn.co.jp/world/35240816.html?ref=rss</link>
        <description>アフリカ西部ナイジェリア北中部ナイジャ州にあるカトリック系私立学校が武装集団に襲撃された事件で、拉致された生徒のうち50人が脱出して家族の元へ戻った。ナイジェリア・キリスト教協会（CAN）が23日に明らかにした。

同協会によると、武装集団は21日に学校を襲撃して児童生徒303人と教員12人を誘拐した。連れ去られたのは男女両方の児童や生徒で、中には10歳の子どももいた。

21日から22日にかけて脱出した子どもたちは...&lt;br clear='left'&gt;&lt;a href='https://www.cnn.co.jp/world/35240816.html?ref=rss'&gt;&lt;img src='https://www.cnn.co.jp/storage/2025/11/24/577c413746394eee9242beddb80c9b59/t/768/511/d/large-gettyimages-2247525662.jpg'&gt;&lt;/a&gt;</description>
    </item>
    <item rdf:about="https://www.cnn.co.jp/world/35240815.html?ref=rss">
        <dc:format>text/html</dc:format>
        <dc:date>2025-11-24T09:58:00+09:00</dc:date>
        <title>イスラエル、レバノン首都を空爆　ヒズボラ軍事部門トップを殺害と発表</title>
        <link>https://www.cnn.co.jp/world/35240815.html?ref=rss</link>
        <description>イスラエル軍はレバノンの首都ベイルート南部を空爆し、イスラム組織ヒズボラのナンバー2を殺害したと発表した。レバノン保健省によると、この攻撃で5人が死亡、28人が負傷した。

イスラエル軍によると、殺害したのはヒズボラ軍事部門トップのハイタム・アリ・タバタバイ参謀総長。「ヒズボラの増強を食い止め、イスラエル国家に危害を加えようとする相手に打撃を与えることを意図した攻撃」と位置付けている。

ヒズボラは23...&lt;br clear='left'&gt;&lt;a href='https://www.cnn.co.jp/world/35240815.html?ref=rss'&gt;&lt;img src='https://www.cnn.co.jp/storage/2025/11/24/9677cc8154efd040e4dbb0768299297a/t/768/511/d/large-gettyimages-2247523747.jpg'&gt;&lt;/a&gt;</description>
    </item>
    <item rdf:about="https://www.cnn.co.jp/fringe/35240810.html?ref=rss">
        <dc:format>text/html</dc:format>
        <dc:date>2025-11-23T17:41:00+09:00</dc:date>
        <title>今いちばん「熱い」場所、サウナが世界で脚光を浴びる理由</title>
        <link>https://www.cnn.co.jp/fringe/35240810.html?ref=rss</link>
        <description>セ氏100度の高温の小さな木の箱の中で、半裸の見知らぬ人たちに囲まれて汗をかくなど、休息やリラクゼーションというよりサディスティックな拷問のように感じる人もいるかもしれない。しかし一方で、サウナが好きでたまらない人もいる。

今、世界中で人々はサウナに夢中になりつつある。英国サウナ協会によると、英国では公衆サウナの数が2023年の45カ所から、今年はすでに147カ所まで増加しているという。またニュージーラン...&lt;br clear='left'&gt;&lt;a href='https://www.cnn.co.jp/fringe/35240810.html?ref=rss'&gt;&lt;img src='https://www.cnn.co.jp/storage/2025/11/23/7b5f5eb32f5f4866dc335bf4b24a4ef9/t/768/431/d/visit-tampere-tohlopin-tynnyrisauna-tohloppi-sauna-winter-talvi-2020-laura-vanzo-41.jpg'&gt;&lt;/a&gt;</description>
    </item>
    <item rdf:about="https://www.cnn.co.jp/tech/35240809.html?ref=rss">
        <dc:format>text/html</dc:format>
        <dc:date>2025-11-23T17:07:00+09:00</dc:date>
        <title>北朝鮮工作員、米AI企業を標的に偽の求人ポータル運営</title>
        <link>https://www.cnn.co.jp/tech/35240809.html?ref=rss</link>
        <description>北朝鮮の工作員が米国のAI（人工知能）企業や暗号資産（仮想通貨）企業を狙い、偽の求人応募用プラットフォームを立ち上げていたことがわかった。セキュリティー企業バリディンの研究者が明らかにした。金正恩（キムジョンウン）政権のために資金や技術を盗み出す新たな手口だという。

米国の主要企業への侵入を狙う北朝鮮の長年の作戦に新たな手段が加わった形だ。バリディンによれば、これまでのように企業の社員を装うだけ...&lt;br clear='left'&gt;&lt;a href='https://www.cnn.co.jp/tech/35240809.html?ref=rss'&gt;&lt;img src='https://www.cnn.co.jp/storage/2025/11/23/37f90254146e854999ad73cac86cc1fb/t/768/513/d/large-gettyimages-2181383176.jpg'&gt;&lt;/a&gt;</description>
    </item>
    <item rdf:about="https://www.cnn.co.jp/world/35240808.html?ref=rss">
        <dc:format>text/html</dc:format>
        <dc:date>2025-11-23T15:59:00+09:00</dc:date>
        <title>ドローン革命がウクライナの防衛に圧力、ロシアはいかに戦場の変化に適応したのか</title>
        <link>https://www.cnn.co.jp/world/35240808.html?ref=rss</link>
        <description>ロシアの首都モスクワに拠点を置く極秘のロシア部隊がドローン（無人機）での戦いの様相を一変させ、これまでウクライナ側が優位だった分野を弱点へと転じさせている。

この部隊は「ルビコン」と呼ばれ、昨年6月にベロウソフ国防相が就任して以降、急速に存在感を増してきた。ロシア国営メディアが公開した動画によれば、ベロウソフ氏は2024年10月に部隊本部を訪問し、開発中の各種のドローンを視察した。

「ルビコン（正式名...&lt;br clear='left'&gt;&lt;a href='https://www.cnn.co.jp/world/35240808.html?ref=rss'&gt;&lt;img src='https://www.cnn.co.jp/storage/2025/11/23/4d9769b4c93bc52aab3a03331106cf2b/t/768/511/d/-3-ukraine-crisis-attack-odesa.jpg'&gt;&lt;/a&gt;</description>
    </item>
    <item rdf:about="https://www.cnn.co.jp/world/35240807.html?ref=rss">
        <dc:format>text/html</dc:format>
        <dc:date>2025-11-23T15:28:00+09:00</dc:date>
        <title>COP30、合意成立も化石燃料脱却への工程表では折り合えず　紛糾の末</title>
        <link>https://www.cnn.co.jp/world/35240807.html?ref=rss</link>
        <description>ブラジルで開催されていた国連の気候変動会議（COP30）が22日に閉幕し、深刻化する気候変動への適応を支援する資金を3倍に増やすことで合意した。だが、根深い分裂で協議が決裂しそうになる場面もあり、化石燃料からの脱却に向けたロードマップ（工程表）では合意できなかった。

アマゾンの玄関口として知られる港湾都市ベレンで、190カ国以上の代表団により2週間以上にわたって交渉が行われ、協議は次第に緊張の度合いを深め...&lt;br clear='left'&gt;&lt;a href='https://www.cnn.co.jp/world/35240807.html?ref=rss'&gt;&lt;img src='https://www.cnn.co.jp/storage/2025/11/23/9c23d05fc3f3192930ce16ac1c1c213e/t/768/511/d/2025-11-19t201411z-281351207-rc2vzhad8jak-rtrmadp-3-climate-cop30.jpg'&gt;&lt;/a&gt;</description>
    </item>
    <item rdf:about="https://www.cnn.co.jp/world/35240806.html?ref=rss">
        <dc:format>text/html</dc:format>
        <dc:date>2025-11-23T13:58:00+09:00</dc:date>
        <title>ブラジル前大統領を拘束、逃亡の恐れ　近日中に刑期開始の予定</title>
        <link>https://www.cnn.co.jp/world/35240806.html?ref=rss</link>
        <description>ブラジルのジャイル・ボルソナーロ前大統領が22日、自宅軟禁からの逃走を試みた疑いがあるとして拘束された。当局が明らかにした。

ボルソナーロ氏は数日後にクーデター未遂を主導した罪などで服役を開始する予定だった。ボルソナーロ氏の訴追については、米国のトランプ政権が強く批判している。

米国のランドー国務副長官は22日、X（旧ツイッター）への投稿で、米国はボルソナーロ氏の拘束について「深刻な懸念」を抱いてい...&lt;br clear='left'&gt;&lt;a href='https://www.cnn.co.jp/world/35240806.html?ref=rss'&gt;&lt;img src='https://www.cnn.co.jp/storage/2025/11/23/ff8594e45f6f87ade9ed13525f49a9e8/t/768/510/d/large-adp-3-brazil-bolsonaro.jpg'&gt;&lt;/a&gt;</description>
    </item>
    <item rdf:about="https://www.cnn.co.jp/travel/35240804.html?ref=rss">
        <dc:format>text/html</dc:format>
        <dc:date>2025-11-23T13:22:00+09:00</dc:date>
        <title>最高時速250キロで走行可能、高速鉄道をお披露目　エジプト</title>
        <link>https://www.cnn.co.jp/travel/35240804.html?ref=rss</link>
        <description>独シーメンス・モビリティが先ごろ公開した高速鉄道車両により、エジプトでは近く旅行者や重要貨物の輸送が高速化される可能性がある。

最高時速250キロで走行可能なシーメンスの高速列車「ヴェラロ」の新型車両が今月、エジプトのニューカイロで開催された交通物流展示会「トランスMEA 2025」で初公開された。

座席数489の高速列車41編成が、エジプトが計画する全長2000キロの高速鉄道網に投入される。シーメンスによれば、...&lt;br clear='left'&gt;&lt;a href='https://www.cnn.co.jp/travel/35240804.html?ref=rss'&gt;&lt;img src='https://www.cnn.co.jp/storage/2025/11/23/a3c8083ea57081f8a71ca62844c88a52/t/768/511/d/large-axx20080442-02-300dpi-20251112150427796.jpg'&gt;&lt;/a&gt;</description>
    </item>
    <item rdf:about="https://www.cnn.co.jp/usa/35240805.html?ref=rss">
        <dc:format>text/html</dc:format>
        <dc:date>2025-11-23T12:59:00+09:00</dc:date>
        <title>ケネディ元米大統領の孫、末期がんと診断され余命1年未満　ケネディ家に新たな悲劇</title>
        <link>https://www.cnn.co.jp/usa/35240805.html?ref=rss</link>
        <description>ジョン・F・ケネディ元米大統領の孫、タチアナ・シュロスバーグさん（35）は22日、末期がんと診断され、医師から余命1年未満と告げられたことを明らかにした。

シュロスバーグさんは米誌ニューヨーカーに寄せたエッセーで、昨年、まれな遺伝子変異である3番染色体の逆位を伴う急性骨髄性白血病（AML）と診断されたことを明かした。この遺伝子異常はAMLの症例の2%未満に見られる。

医師たちは、シュロスバーグさんが昨年5月に...&lt;br clear='left'&gt;&lt;a href='https://www.cnn.co.jp/usa/35240805.html?ref=rss'&gt;&lt;img src='https://www.cnn.co.jp/storage/2025/11/23/fe27cbffdd957741cfad9e8b604cad89/t/768/511/d/gettyimages-1172628181.jpg'&gt;&lt;/a&gt;</description>
    </item>
    <item rdf:about="https://www.cnn.co.jp/fringe/35240803.html?ref=rss">
        <dc:format>text/html</dc:format>
        <dc:date>2025-11-23T11:26:00+09:00</dc:date>
        <title>オオカミが道具を使用？、カナダで初めて撮影</title>
        <link>https://www.cnn.co.jp/fringe/35240803.html?ref=rss</link>
        <description>カナダ西部ブリティッシュコロンビア州で、オオカミが道具を使っている様子を捉えた映像が撮影された。研究者によれば、オオカミによるこうした行動が記録されたのは今回が初めて。

先住民を研究するチームが、カニ漁用のわなが繰り返し壊されているのを不審に思い、カメラを設置した。クマやカワウソの姿が見られるだろうと予想していたが、撮影された光景に研究者は驚いた。

そこには、オオカミが泳いでブイに近づき、それ...&lt;br clear='left'&gt;&lt;a href='https://www.cnn.co.jp/fringe/35240803.html?ref=rss'&gt;&lt;img src='https://www.cnn.co.jp/storage/2025/11/23/bd0d035f9c23f9b73e8520151982c4a7/t/768/432/d/115351-wolves-tools-thumb.jpg'&gt;&lt;/a&gt;</description>
    </item>
</rdf:RDF>
